whois/__init__.py
whois/whois.py
sample_whois-0.2.dist-info/METADATA
sample_whois-0.2.dist-info/WHEEL
sample_whois-0.2.dist-info/top_level.txt
sample_whois-0.2.dist-info/RECORD
