Metadata-Version: 2.1
Name: sample-whois
Version: 0.2
Summary: 域名注册信息查询工具
Home-page: https://github.com/Lion-Li
Author: lixiang
Author-email: 121365554@qq.com
License: MIT
Platform: UNKNOWN
Classifier: Development Status :: 3 - Alpha
Classifier: Intended Audience :: Developers
Classifier: Topic :: Software Development :: Libraries
Classifier: Programming Language :: Python :: 3.6
